mautrix_appservice/__init__.py
mautrix_appservice/appservice.py
mautrix_appservice/errors.py
mautrix_appservice/intent_api.py
mautrix_appservice/state_store.py
mautrix_appservice-0.3.11.dist-info/LICENSE
mautrix_appservice-0.3.11.dist-info/METADATA
mautrix_appservice-0.3.11.dist-info/WHEEL
mautrix_appservice-0.3.11.dist-info/top_level.txt
mautrix_appservice-0.3.11.dist-info/RECORD
