Metadata-Version: 2.1
Name: mautrix-appservice
Version: 0.3.11
Summary: A Python 3 asyncio-based Matrix application service framework.
Home-page: https://github.com/tulir/mautrix-appservice-python
Author: Tulir Asokan
Author-email: tulir@maunium.net
License: UNKNOWN
Platform: UNKNOWN
Classifier: Development Status :: 4 - Beta
Classifier: License :: OSI Approved :: MIT License
Classifier: Topic :: Communications :: Chat
Classifier: Programming Language :: Python
Classifier: Programming Language :: Python :: 3
Classifier: Programming Language :: Python :: 3.5
Classifier: Programming Language :: Python :: 3.6
Requires-Python: ~=3.5
Requires-Dist: aiohttp (<4,>=3.0.1)
Requires-Dist: future-fstrings (>=0.4.2)
Provides-Extra: detect_mimetype
Requires-Dist: python-magic (<0.5,>=0.4.15) ; extra == 'detect_mimetype'
